ch9329/__init__.py
ch9329/config.py
ch9329/exceptions.py
ch9329/hid.py
ch9329/keyboard.py
ch9329/mouse.py
ch9329/py.typed
ch9329/utils.py
ch9329/tools/__init__.py
ch9329/tools/lsch9329.py
ch9329-1.2.7.dist-info/LICENSE
ch9329-1.2.7.dist-info/METADATA
ch9329-1.2.7.dist-info/WHEEL
ch9329-1.2.7.dist-info/entry_points.txt
ch9329-1.2.7.dist-info/top_level.txt
ch9329-1.2.7.dist-info/RECORD
