Metadata-Version: 2.1
Name: ch9329
Version: 1.2.7
Summary: Python module to control ch9329
Author-email: Pradish Bijukchhe <pradish@sandbox.com.np>
License: Copyright (c) 2018 The Python Packaging Authority
Project-URL: Homepage, https://github.com/sandbox-pokhara/ch9329
Project-URL: Issues, https://github.com/sandbox-pokhara/ch9329/issues
Classifier: Programming Language :: Python :: 3
Requires-Python: >=3
License-File: LICENSE
Requires-Dist: pyserial
Provides-Extra: dev
Requires-Dist: pytest ; extra == 'dev'
